Workbook
Name SchoolYear: Settings!$C$5
Name FirstDayOfSchool: Settings!$C$6
Name TotalBudget: Settings!$C$7
Name FamilySize: Settings!$C$8
Name TaxRate: Settings!$C$9
Name TodayDate: Settings!$C$10
Name CategoryList: Settings!$E$6:$E$14
Name PriorityList: Settings!$F$6:$F$8
Name StatusList: Settings!$G$6:$G$9
Name SubjectList: Settings!$H$6:$H$15
Name StoreList: Settings!$E$21:$E$26
Name GradeList: Settings!$F$21:$F$35
Name YesNoList: Settings!$G$21:$G$22
Name TransportList: Settings!$H$21:$H$25
Name SupActual: Supplies!$H$5:$H$64
Name SupEst: Supplies!$G$5:$G$64
Name SupPurchased: Supplies!$I$5:$I$64
Name SupItem: Supplies!$B$5:$B$64
Name SupReq: Supplies!$C$5:$C$64
Name SupBought: Supplies!$D$5:$D$64
Name BudgetCategories: Budget!$A$5:$A$13
Name BudgetPlanned: Budget!$B$5:$B$13
Name BudgetActual: Budget!$C$5:$C$13
Name BudgetTotalPlanned: Budget!$B$14
Name BudgetTotalActual: Budget!$C$14
Name AsgStatus: Assignments!$E$5:$E$54
Name AsgDue: Assignments!$C$5:$C$54
Name AsgSubject: Assignments!$A$5:$A$54

Sheet Dashboard
A1: 🎒 BACK-TO-SCHOOL COMMAND CENTER
A2: Plan · Budget · Organize · Prepare — one premium dashboard for the whole school year.
B4: 💵 Total Budget | D4: 💳 Total Spent | F4: 🧮 Remaining | H4: ⏳ Days Until School
B5: =TotalBudget | D5: =BudgetTotalActual | F5: =TotalBudget-BudgetTotalActual | H5: =MAX(FirstDayOfSchool-TODAY(),0)
B7: 🛒 Items Purchased | D7: 📋 Items Remaining | F7: 🎒 Supply Completion | H7: ✅ Assignments Done
B8: =SUMPRODUCT((SupPurchased="Yes")*1) | D8: =SUMPRODUCT((SupItem<>"")*(SupPurchased<>"Yes")) | F8: =IFERROR(SUMPRODUCT((SupPurchased="Yes")*1)/SUMPRODUCT((SupItem<>"")*1),0) | H8: =IFERROR(SUMPRODUCT((AsgStatus="Complete")*1)/SUMPRODUCT((AsgStatus<>"")*1),0)
B10: QUICK NAVIGATION
B11: Shopping List | C11: Budget | D11: Calendar | E11: Students | F11: Assignments | G11: Meals | H11: Emergency
B13: ANALYTICS
B34: Back-to-School Command Center v1.0 · Edit Settings → Total Budget · First Day · Add items on Supplies

Sheet Students
A1: 👨‍🎓 STUDENT PROFILES
A2: One section per student. Duplicate the block for additional kids.
B4: STUDENT
B5: Name | C5: Emma Carter | E5: Grade | F5: 4
B6: School | C6: Lincoln Elementary | E6: Teacher | F6: Ms. Hayes
B7: Student ID | C7: LE-2024-118 | E7: Start Date | F7: 46267
B8: Allergies | C8: Peanuts | E8: Emergency Contact | F8: Mom: (555) 412-7833
B9: Transportation | C9: Bus | E9: Locker # | F9: —
B10: Bus Route | C10: Route 14 | E10: Homeroom | F10: Rm 104
B13: STUDENT
B14: Name | C14: Liam Carter | E14: Grade | F14: 8
B15: School | C15: Roosevelt Middle | E15: Teacher | F15: Mr. Patel
B16: Student ID | C16: RM-2024-441 | E16: Start Date | F16: 46267
B17: Allergies | C17: None | E17: Emergency Contact | F17: Dad: (555) 412-7901
B18: Transportation | C18: Carpool | E18: Locker # | F18: 212
B19: Bus Route | C19: — | E19: Homeroom | F19: Rm 8B

Sheet Supplies
A1: 📚 SCHOOL SUPPLY TRACKER
A2: Track every item from list to checkout. Formulas auto-tally.
A4: Category | B4: Item | C4: Req Qty | D4: Bought Qty | E4: Remaining | F4: Store | G4: Est. Price | H4: Actual Price | I4: Purchased | J4: Priority | K4: Notes
A5: Supplies | B5: Backpack | C5: 1 | D5: 1 | E5: =IF(C5="","",MAX(C5-IFERROR(D5,0),0)) | F5: Target | G5: 39.99 | H5: 34.99 | I5: Yes | J5: High | K5: Black with side pocket
A6: Supplies | B6: Pencil case | C6: 2 | D6: 0 | E6: =IF(C6="","",MAX(C6-IFERROR(D6,0),0)) | F6: Amazon | G6: 8.99 | I6: No | J6: Medium | K6: Need two: one per child
A7: Supplies | B7: Pencils #2 (12pk) | C7: 4 | D7: 3 | E7: =IF(C7="","",MAX(C7-IFERROR(D7,0),0)) | F7: Walmart | G7: 3.49 | H7: 3.49 | I7: No | J7: High
A8: Supplies | B8: Erasers | C8: 6 | D8: 4 | E8: =IF(C8="","",MAX(C8-IFERROR(D8,0),0)) | F8: Walmart | G8: 1.99 | H8: 1.99 | I8: No | J8: Low
A9: Supplies | B9: Glue sticks | C9: 12 | D9: 6 | E9: =IF(C9="","",MAX(C9-IFERROR(D9,0),0)) | F9: Staples | G9: 0.99 | H9: 0.99 | I9: No | J9: Medium
A10: Supplies | B10: Notebook (wide-rule) | C10: 8 | D10: 8 | E10: =IF(C10="","",MAX(C10-IFERROR(D10,0),0)) | F10: Target | G10: 1.49 | H10: 1.29 | I10: Yes | J10: High | K10: All purchased
A11: Supplies | B11: Composition books | C11: 4 | D11: 0 | E11: =IF(C11="","",MAX(C11-IFERROR(D11,0),0)) | F11: Staples | G11: 2.49 | I11: No | J11: Medium
A12: Supplies | B12: Folders | C12: 6 | D12: 3 | E12: =IF(C12="","",MAX(C12-IFERROR(D12,0),0)) | F12: Target | G12: 0.79 | H12: 0.79 | I12: No | J12: Medium
A13: Supplies | B13: Binders 1" | C13: 3 | D13: 1 | E13: =IF(C13="","",MAX(C13-IFERROR(D13,0),0)) | F13: Staples | G13: 4.99 | H13: 4.99 | I13: No | J13: High
A14: Supplies | B14: Highlighters (4pk) | C14: 2 | D14: 2 | E14: =IF(C14="","",MAX(C14-IFERROR(D14,0),0)) | F14: Amazon | G14: 4.49 | H14: 4.49 | I14: Yes | J14: Low
A15: Electronics | B15: Laptop bag | C15: 1 | D15: 0 | E15: =IF(C15="","",MAX(C15-IFERROR(D15,0),0)) | F15: Amazon | G15: 24.99 | I15: No | J15: High | K15: 13" sleeve
A16: Electronics | B16: USB-C charger | C16: 2 | D16: 1 | E16: =IF(C16="","",MAX(C16-IFERROR(D16,0),0)) | F16: Amazon | G16: 19.99 | H16: 19.99 | I16: No | J16: High
A17: Electronics | B17: Headphones (wired) | C17: 2 | D17: 2 | E17: =IF(C17="","",MAX(C17-IFERROR(D17,0),0)) | F17: Target | G17: 12.99 | H17: 12.99 | I17: Yes | J17: Medium
A18: Clothing | B18: School polo | C18: 5 | D18: 2 | E18: =IF(C18="","",MAX(C18-IFERROR(D18,0),0)) | F18: Target | G18: 14.99 | H18: 14.99 | I18: No | J18: High | K18: Navy
A19: Clothing | B19: Khaki pants | C19: 3 | D19: 1 | E19: =IF(C19="","",MAX(C19-IFERROR(D19,0),0)) | F19: Target | G19: 19.99 | H19: 19.99 | I19: No | J19: High
A20: Shoes | B20: Sneakers | C20: 2 | D20: 1 | E20: =IF(C20="","",MAX(C20-IFERROR(D20,0),0)) | F20: Local | G20: 44.99 | H20: 39.99 | I20: No | J20: High | K20: Size 4 & 7
A21: Sports | B21: Soccer cleats | C21: 1 | D21: 0 | E21: =IF(C21="","",MAX(C21-IFERROR(D21,0),0)) | F21: Local | G21: 54.99 | I21: No | J21: Medium | K21: Try-on 8/24
A22: Lunch Supplies | B22: Lunch box | C22: 2 | D22: 2 | E22: =IF(C22="","",MAX(C22-IFERROR(D22,0),0)) | F22: Target | G22: 12.99 | H22: 12.99 | I22: Yes | J22: High
A23: Lunch Supplies | B23: Water bottle | C23: 2 | D23: 1 | E23: =IF(C23="","",MAX(C23-IFERROR(D23,0),0)) | F23: Target | G23: 9.99 | H23: 9.99 | I23: No | J23: High
A24: Fees | B24: Registration fee | C24: 1 | D24: 0 | E24: =IF(C24="","",MAX(C24-IFERROR(D24,0),0)) | F24: Other | G24: 125 | I24: No | J24: High | K24: Due 8/20
A25: Fees | B25: Field trip deposit | C25: 1 | D25: 0 | E25: =IF(C25="","",MAX(C25-IFERROR(D25,0),0)) | F25: Other | G25: 35 | I25: No | J25: Medium
A26: Miscellaneous | B26: Locker organizer | C26: 1 | D26: 0 | E26: =IF(C26="","",MAX(C26-IFERROR(D26,0),0)) | F26: Amazon | G26: 16.99 | I26: No | J26: Low
E27: =IF(C27="","",MAX(C27-IFERROR(D27,0),0))
E28: =IF(C28="","",MAX(C28-IFERROR(D28,0),0))
E29: =IF(C29="","",MAX(C29-IFERROR(D29,0),0))
E30: =IF(C30="","",MAX(C30-IFERROR(D30,0),0))
E31: =IF(C31="","",MAX(C31-IFERROR(D31,0),0))
E32: =IF(C32="","",MAX(C32-IFERROR(D32,0),0))
E33: =IF(C33="","",MAX(C33-IFERROR(D33,0),0))
E34: =IF(C34="","",MAX(C34-IFERROR(D34,0),0))
E35: =IF(C35="","",MAX(C35-IFERROR(D35,0),0))
E36: =IF(C36="","",MAX(C36-IFERROR(D36,0),0))
E37: =IF(C37="","",MAX(C37-IFERROR(D37,0),0))
E38: =IF(C38="","",MAX(C38-IFERROR(D38,0),0))
... E64: =IF(C64="","",MAX(C64-IFERROR(D64,0),0))

Sheet Budget
A1: 💰 BACK-TO-SCHOOL BUDGET
A2: Plan, track, and check variance across categories.
A4: Category | B4: Planned | C4: Actual | D4: Variance | E4: % Spent | G4: BUDGET KPIs
A5: Supplies | B5: 200 | C5: =IFERROR(SUMIFS(SupActual,Supplies!$A$5:$A$64,A5),0) | D5: =B5-C5 | E5: =IFERROR(C5/B5,0) | G5: Planned Budget | H5: =BudgetTotalPlanned
A6: Clothing | B6: 260 | C6: =IFERROR(SUMIFS(SupActual,Supplies!$A$5:$A$64,A6),0) | D6: =B6-C6 | E6: =IFERROR(C6/B6,0) | G6: Actual Spending | H6: =BudgetTotalActual
A7: Shoes | B7: 120 | C7: =IFERROR(SUMIFS(SupActual,Supplies!$A$5:$A$64,A7),0) | D7: =B7-C7 | E7: =IFERROR(C7/B7,0) | G7: Remaining | H7: =TotalBudget-BudgetTotalActual
A8: Electronics | B8: 180 | C8: =IFERROR(SUMIFS(SupActual,Supplies!$A$5:$A$64,A8),0) | D8: =B8-C8 | E8: =IFERROR(C8/B8,0) | G8: % Spent | H8: =IFERROR(BudgetTotalActual/TotalBudget,0)
A9: Sports | B9: 90 | C9: =IFERROR(SUMIFS(SupActual,Supplies!$A$5:$A$64,A9),0) | D9: =B9-C9 | E9: =IFERROR(C9/B9,0)
A10: Lunch Supplies | B10: 60 | C10: =IFERROR(SUMIFS(SupActual,Supplies!$A$5:$A$64,A10),0) | D10: =B10-C10 | E10: =IFERROR(C10/B10,0)
A11: Fees | B11: 180 | C11: =IFERROR(SUMIFS(SupActual,Supplies!$A$5:$A$64,A11),0) | D11: =B11-C11 | E11: =IFERROR(C11/B11,0)
A12: Transportation | B12: 60 | C12: =IFERROR(SUMIFS(SupActual,Supplies!$A$5:$A$64,A12),0) | D12: =B12-C12 | E12: =IFERROR(C12/B12,0)
A13: Miscellaneous | B13: 50 | C13: =IFERROR(SUMIFS(SupActual,Supplies!$A$5:$A$64,A13),0) | D13: =B13-C13 | E13: =IFERROR(C13/B13,0)
A14: TOTAL | B14: =SUM(B5:B13) | C14: =SUM(C5:C13) | D14: =SUM(D5:D13) | E14: =IFERROR(C14/B14,0)

Sheet Clothing
A1: 👕 CLOTHING INVENTORY
A2: Sizes, quantities, and what's left to buy.
A4: Category | B4: Item | C4: Size | D4: Qty Needed | E4: Qty Owned | F4: Cost / Unit | G4: Status | H4: Notes
A5: Shirts | B5: Polo (Navy) | C5: S | D5: 5 | E5: 2 | F5: 14.99 | G5: =IF(D5="","",IF(E5>=D5,"Complete",IF(E5=0,"Not Started","In Progress")))
A6: Shirts | B6: Polo (White) | C6: S | D6: 3 | E6: 1 | F6: 14.99 | G6: =IF(D6="","",IF(E6>=D6,"Complete",IF(E6=0,"Not Started","In Progress")))
A7: Shirts | B7: Long sleeve tee | C7: S | D7: 4 | E7: 4 | F7: 9.99 | G7: =IF(D7="","",IF(E7>=D7,"Complete",IF(E7=0,"Not Started","In Progress")))
A8: Pants | B8: Khaki | C8: 8 | D8: 3 | E8: 1 | F8: 19.99 | G8: =IF(D8="","",IF(E8>=D8,"Complete",IF(E8=0,"Not Started","In Progress")))
A9: Pants | B9: Jeans | C9: 8 | D9: 2 | E9: 2 | F9: 24.99 | G9: =IF(D9="","",IF(E9>=D9,"Complete",IF(E9=0,"Not Started","In Progress")))
A10: Shoes | B10: Sneakers | C10: 4 | D10: 1 | E10: 0 | F10: 39.99 | G10: =IF(D10="","",IF(E10>=D10,"Complete",IF(E10=0,"Not Started","In Progress"))) | H10: Order online
A11: Shoes | B11: Dress shoes | C11: 4 | D11: 1 | E11: 1 | F11: 29.99 | G11: =IF(D11="","",IF(E11>=D11,"Complete",IF(E11=0,"Not Started","In Progress")))
A12: Jackets | B12: Light jacket | C12: S | D12: 1 | E12: 0 | F12: 34.99 | G12: =IF(D12="","",IF(E12>=D12,"Complete",IF(E12=0,"Not Started","In Progress")))
A13: Jackets | B13: Winter coat | C13: S | D13: 1 | E13: 1 | F13: 59.99 | G13: =IF(D13="","",IF(E13>=D13,"Complete",IF(E13=0,"Not Started","In Progress"))) | H13: Last year still fits
A14: Uniforms | B14: School sweater | C14: S | D14: 2 | E14: 0 | F14: 24.99 | G14: =IF(D14="","",IF(E14>=D14,"Complete",IF(E14=0,"Not Started","In Progress")))
A15: Gym Clothes | B15: Athletic shorts | C15: S | D15: 3 | E15: 2 | F15: 11.99 | G15: =IF(D15="","",IF(E15>=D15,"Complete",IF(E15=0,"Not Started","In Progress")))
A16: Gym Clothes | B16: Performance tee | C16: S | D16: 3 | E16: 1 | F16: 9.99 | G16: =IF(D16="","",IF(E16>=D16,"Complete",IF(E16=0,"Not Started","In Progress")))
A17: Accessories | B17: Belt | C17: S | D17: 2 | E17: 1 | F17: 7.99 | G17: =IF(D17="","",IF(E17>=D17,"Complete",IF(E17=0,"Not Started","In Progress")))
A18: Accessories | B18: Socks (6pk) | C18: M | D18: 2 | E18: 1 | F18: 8.99 | G18: =IF(D18="","",IF(E18>=D18,"Complete",IF(E18=0,"Not Started","In Progress")))
A19: Accessories | B19: Hat | C19: S | D19: 1 | E19: 0 | F19: 12.99 | G19: =IF(D19="","",IF(E19>=D19,"Complete",IF(E19=0,"Not Started","In Progress")))
G20: =IF(D20="","",IF(E20>=D20,"Complete",IF(E20=0,"Not Started","In Progress")))
G21: =IF(D21="","",IF(E21>=D21,"Complete",IF(E21=0,"Not Started","In Progress")))
G22: =IF(D22="","",IF(E22>=D22,"Complete",IF(E22=0,"Not Started","In Progress")))
G23: =IF(D23="","",IF(E23>=D23,"Complete",IF(E23=0,"Not Started","In Progress")))
G24: =IF(D24="","",IF(E24>=D24,"Complete",IF(E24=0,"Not Started","In Progress")))
G25: =IF(D25="","",IF(E25>=D25,"Complete",IF(E25=0,"Not Started","In Progress")))
G26: =IF(D26="","",IF(E26>=D26,"Complete",IF(E26=0,"Not Started","In Progress")))
G27: =IF(D27="","",IF(E27>=D27,"Complete",IF(E27=0,"Not Started","In Progress")))
G28: =IF(D28="","",IF(E28>=D28,"Complete",IF(E28=0,"Not Started","In Progress")))
G29: =IF(D29="","",IF(E29>=D29,"Complete",IF(E29=0,"Not Started","In Progress")))
G30: =IF(D30="","",IF(E30>=D30,"Complete",IF(E30=0,"Not Started","In Progress")))
G31: =IF(D31="","",IF(E31>=D31,"Complete",IF(E31=0,"Not Started","In Progress")))
... G34: =IF(D34="","",IF(E34>=D34,"Complete",IF(E34=0,"Not Started","In Progress")))

Sheet Schedule
A1: 📅 WEEKLY CLASS SCHEDULE
A2: Color-coded by subject. Drag in homework notes per slot.
A4: TIME | B4: Monday | C4: Tuesday | D4: Wednesday | E4: Thursday | F4: Friday
A5: 8:00 – 8:55 | B5: Math · Hayes · R104 | C5: Math · Hayes · R104 | D5: Math · Hayes · R104 | E5: Math · Hayes · R104 | F5: Math · Hayes · R104
A6: 9:00 – 9:55 | B6: English · Brooks · R208 | C6: Science · Patel · R301 | D6: English · Brooks · R208 | E6: Science · Patel · R301 | F6: English · Brooks · R208
A7: 10:00 – 10:55 | B7: Science · Patel · R301 | C7: English · Brooks · R208 | D7: Science · Patel · R301 | E7: English · Brooks · R208 | F7: Science · Patel · R301
A8: 11:00 – 11:55 | B8: History · Reed · R112 | C8: Art · Lin · R150 | D8: History · Reed · R112 | E8: Tech · Reyes · Lab2 | F8: Music · Park · R220
A9: 12:00 – 12:45 (Lunch) | B9: LUNCH | C9: LUNCH | D9: LUNCH | E9: LUNCH | F9: LUNCH
A10: 12:50 – 1:45 | B10: PE · Gomez · Gym | C10: PE · Gomez · Gym | D10: PE · Gomez · Gym | E10: PE · Gomez · Gym | F10: PE · Gomez · Gym
A11: 1:50 – 2:45 | B11: Spanish · Ortega · R141 | C11: Spanish · Ortega · R141 | D11: Spanish · Ortega · R141 | E11: Spanish · Ortega · R141 | F11: Spanish · Ortega · R141
A12: 2:50 – 3:30 | B12: Study Hall · R104 | C12: Study Hall · R104 | D12: Study Hall · R104 | E12: Club: Robotics · Lab2 | F12: Study Hall · R104

Sheet Assignments
A1: 📝 ASSIGNMENT TRACKER
A2: Due dates, priorities, status — and live overdue flags.
A4: Subject | B4: Assignment | C4: Due Date | D4: Priority | E4: Status | F4: Grade | G4: Notes | H4: Days Until
A5: Math | B5: Ch 3 problem set | C5: 46199 | D5: High | E5: Complete | F5: 92 | G5: Showed all work | H5: =IF(C5="","",C5-TODAY())
A6: English | B6: Book report: Hatchet | C6: 46203 | D6: High | E6: In Progress | G6: Outline done | H6: =IF(C6="","",C6-TODAY())
A7: Science | B7: Lab write-up | C7: 46200 | D7: Medium | E7: Not Started | G7: Need lab partner notes | H7: =IF(C7="","",C7-TODAY())
A8: History | B8: Civil War timeline | C8: 46206 | D8: Medium | E8: Not Started | H8: =IF(C8="","",C8-TODAY())
A9: Art | B9: Self portrait | C9: 46210 | D9: Low | E9: In Progress | G9: Sketch stage | H9: =IF(C9="","",C9-TODAY())
A10: Tech | B10: Robotics build log | C10: 46201 | D10: High | E10: In Progress | G10: Due end of day | H10: =IF(C10="","",C10-TODAY())
A11: Spanish | B11: Vocab quiz prep | C11: 46202 | D11: Medium | E11: Not Started | H11: =IF(C11="","",C11-TODAY())
A12: Math | B12: Quiz: fractions | C12: 46208 | D12: High | E12: Not Started | G12: Study Mon evening | H12: =IF(C12="","",C12-TODAY())
A13: English | B13: Vocabulary list | C13: 46198 | D13: Low | E13: Complete | F13: 100 | H13: =IF(C13="","",C13-TODAY())
A14: Science | B14: Reading: chapters 4–5 | C14: 46204 | D14: Medium | E14: Not Started | H14: =IF(C14="","",C14-TODAY())
H15: =IF(C15="","",C15-TODAY())
H16: =IF(C16="","",C16-TODAY())
H17: =IF(C17="","",C17-TODAY())
H18: =IF(C18="","",C18-TODAY())
H19: =IF(C19="","",C19-TODAY())
H20: =IF(C20="","",C20-TODAY())
H21: =IF(C21="","",C21-TODAY())
H22: =IF(C22="","",C22-TODAY())
H23: =IF(C23="","",C23-TODAY())
H24: =IF(C24="","",C24-TODAY())
H25: =IF(C25="","",C25-TODAY())
H26: =IF(C26="","",C26-TODAY())
... H54: =IF(C54="","",C54-TODAY())

Sheet Extracurricular
A1: 🎯 EXTRACURRICULAR ACTIVITIES
A2: Practices, fees, equipment, and contacts in one view.
A4: Activity | B4: Coach / Instructor | C4: Practice Day | D4: Practice Time | E4: Fee | F4: Equipment Needed | G4: Contact
A5: Soccer (U10) | B5: Coach Reyes | C5: Mon / Wed | D5: 4:30 – 6:00pm | E5: 120 | F5: Cleats, shin guards, ball | G5: reyes@league.org
A6: Robotics Club | B6: Mr. Patel | C6: Thursday | D6: 3:30 – 5:00pm | E6: 45 | F6: Laptop | G6: patel@school.edu
A7: Piano Lessons | B7: Ms. Park | C7: Saturday | D7: 10:00 – 10:30am | E7: 35 | F7: Practice book | G7: (555) 412-8841
A8: Art Workshop | B8: Ms. Lin | C8: Friday | D8: 3:30 – 4:30pm | E8: 25 | F8: Sketchbook, pencils | G8: lin@studio.com
A9: Math Olympiad | B9: Mr. Hayes | C9: Tuesday | D9: 3:30 – 4:30pm | E9: 0 | F9: — | G9: hayes@school.edu
A10: Swimming | B10: Coach Diaz | C10: Sun / Wed | D10: 8:00 – 9:00am | E10: 80 | F10: Swimsuit, goggles, towel | G10: (555) 901-2271

Sheet Calendar
A1: 🗓 SCHOOL-YEAR CALENDAR
A2: Logged events: holidays, exams, meetings, deadlines.
A4: Date | B4: Day | C4: Event | D4: Notes | E4: Type | F4: Student
A5: 46267 | B5: Wed | C5: First day of school | D5: Bus pickup 7:35am | E5: Milestone | F5: All
A6: 46279 | B6: Mon | C6: Picture day | D6: Wear school colors | E6: Picture Day | F6: All
A7: 46286 | B7: Mon | C7: Back-to-school night | D7: 6:30pm – 8:30pm | E7: Parent-Teacher | F7: All
A8: 46304 | B8: Fri | C8: Teacher work day (no school) | E8: Holiday | F8: All
A9: 46321 | B9: Mon | C9: Midterm exam — Math | D9: Bring calculator | E9: Exam | F9: Liam
A10: 46339 | B10: Fri | C10: Field trip — Museum | D10: Permission slip due 11/6 | E10: Field Trip | F10: Emma
A11: 46352 | B11: Thu | C11: Thanksgiving break begins | D11: Return 12/1 | E11: Holiday | F11: All
A12: 46374 | B12: Fri | C12: Winter break begins | D12: Return 1/5 | E12: Holiday | F12: All
A13: 46402 | B13: Fri | C13: Report cards issued | E13: Milestone | F13: All
A14: 46430 | B14: Fri | C14: Parent-teacher conferences | D14: Sign up online | E14: Parent-Teacher | F14: All
A15: 46472 | B15: Fri | C15: Spring break begins | D15: Return 4/5 | E15: Holiday | F15: All
A16: 46531 | B16: Mon | C16: Final exams week | E16: Exam | F16: Liam
A17: 46550 | B17: Fri | C17: Last day of school | D17: Early dismissal 12pm | E17: Milestone | F17: All

Sheet Meals
A1: 🍎 LUNCH & MEAL PLANNER
A2: Weekly meals + auto-build grocery list.
A4: MEAL | B4: Monday | C4: Tuesday | D4: Wednesday | E4: Thursday | F4: Friday | H4: GROCERY LIST
A5: Breakfast | B5: Oatmeal + berries | C5: Yogurt parfait | D5: Scrambled eggs + toast | E5: Smoothie + granola | F5: Pancakes | H5: Bread (whole grain) | I5: 2
A6: Lunch | B6: Turkey wrap + apple | C6: PB&J + carrots | D6: Pasta salad + grapes | E6: Chicken nuggets + cucumber | F6: Cheese pizza slice + orange | H6: Turkey slices | I6: 1
A7: Snack | B7: Trail mix | C7: Cheese stick + crackers | D7: Apple slices + PB | E7: Granola bar | F7: Veggie chips | H7: Cheese sticks | I7: 8
H8: Apples | I8: 10
H9: Carrots (baby) | I9: 1
A10: DIETARY NOTES | H10: Cucumbers | I10: 2
A11: Emma: peanut allergy — strictly no peanuts in lunch packing. Liam: vegetarian Mondays. Family: gluten-free option preferred Wednesdays. | H11: Yogurt cups | I11: 8
H12: Granola | I12: 1
H13: Trail mix | I13: 1
H14: Eggs (dozen) | I14: 1
H15: Oats | I15: 1
H16: Berries (mixed) | I16: 2
H17: Pasta | I17: 1
H18: Pizza slices (frozen) | I18: 5
H19: Veggie chips | I19: 1

Sheet Emergency
A1: 🚨 EMERGENCY CONTACTS & INFO
A2: Keep this printable and accessible.
A4: FAMILY
A5: Role | B5: Name | C5: Phone | D5: Email / Provider | E5: Notes | BQ5: Email / Provider | BZ5: Notes | CB5: Phone | CD5: Role
A6: Mom | B6: Sarah Carter | C6: (555) 412-7833 | D6: sarah@example.com | E6: Primary
A7: Dad | B7: James Carter | C7: (555) 412-7901 | D7: james@example.com | E7: Secondary
A8: Grandma | B8: Linda Reyes | C8: (555) 904-1320 | D8: linda@example.com | E8: Pickup authorized
A10: MEDICAL
A11: Role | B11: Name | C11: Phone | D11: Email / Provider | E11: Notes | BQ11: Email / Provider | BZ11: Notes | CB11: Phone | CD11: Role
A12: Pediatrician | B12: Dr. Mira Singh | C12: (555) 388-2210 | D12: Westside Pediatrics | E12: Mon–Fri 8–5
A13: Dentist | B13: Dr. Aaron Park | C13: (555) 388-9911 | D13: Park Family Dental
A14: Allergist | B14: Dr. Eleanor Wu | C14: (555) 388-3344 | D14: Allergy Partners | E14: EpiPen: see backpack
A16: SCHOOL
A17: Role | B17: Name | C17: Phone | D17: Email / Provider | E17: Notes | BQ17: Email / Provider | BZ17: Notes | CB17: Phone | CD17: Role
A18: Lincoln Elementary office | B18: — | C18: (555) 200-1188 | D18: lincoln@district.edu | E18: Emma · Rm 104
A19: Roosevelt Middle office | B19: — | C19: (555) 200-2244 | D19: rms@district.edu | E19: Liam · Rm 8B
A20: After-school program | B20: Ms. Hall | C20: (555) 200-7711 | D20: afterschool@district.edu
A22: INSURANCE
A23: Role | B23: Name | C23: Phone | D23: Email / Provider | E23: Notes | BQ23: Email / Provider | BZ23: Notes | CB23: Phone | CD23: Role
A24: Health insurance | B24: BlueShield | C24: 1-800-555-0000 | D24: Member ID: 8821-44A | E24: Group #14422
A25: Dental insurance | B25: DeltaDental | C25: 1-800-555-7700 | D25: Member ID: 8821-44D

Sheet Settings
A1: ⚙ SETTINGS
A2: Configure school year, goals, and dropdowns.
B4: USER CONTROLS | E4: DROPDOWN LISTS
B5: School Year | C5: 2026-2027 | E5: Categories | F5: Priority | G5: Status | H5: Subjects
B6: First Day of School | C6: 46267 | E6: Supplies | F6: High | G6: Not Started | H6: Math
B7: Total Back-to-School Budget | C7: 1200 | E7: Clothing | F7: Medium | G7: In Progress | H7: English
B8: Family Size | C8: 2 | E8: Shoes | F8: Low | G8: Complete | H8: Science
B9: Tax Rate | C9: 0.075 | E9: Electronics | G9: Overdue | H9: History
B10: Today (auto) | C10: =TODAY() | E10: Sports | H10: Art
E11: Lunch Supplies | H11: PE
E12: Fees | H12: Music
E13: Transportation | H13: Tech
E14: Miscellaneous | H14: Spanish
H15: Other
E20: Stores | F20: Grades | G20: Yes / No | H20: Transport
E21: Target | F21: Pre-K | G21: Yes | H21: Bus
E22: Walmart | F22: K | G22: No | H22: Carpool
E23: Amazon | F23: 1 | H23: Walk
E24: Staples | F24: 2 | H24: Bike
E25: Local | F25: 3 | H25: Parent Drop-off
E26: Other | F26: 4
F27: 5
F28: 6
F29: 7
F30: 8
F31: 9
F32: 10
F33: 11
F34: 12
F35: College
