Workbook
Name Restaurant: Settings!$C$6
Name Manager: Settings!$C$7
Name TargetLaborPct: Settings!$C$8
Name SPLHGoal: Settings!$C$9
Name OTLimit: Settings!$C$10
Name PrimeGoal: Settings!$C$11
Name WageGoal: Settings!$C$12
Name Currency: Settings!$C$13
Name RoleList: Settings!$E$7:$E$13
Name StatusList: Settings!$F$7:$F$10
Name YesNoList: Settings!$G$7:$G$8
Name LaborPct: 'Labor Cost Calc'!$C$8
Name SPLH: 'Labor Cost Calc'!$C$10
Name AvgWage: 'Labor Cost Calc'!$C$11
Name SchedName: 'Weekly Schedule'!$B$5:$B$12
Name SchedWage: 'Weekly Schedule'!$D$5:$D$12
Name SchedHours: 'Weekly Schedule'!$L$5:$L$12
Name SchedCost: 'Weekly Schedule'!$M$5:$M$12
Name TotalHours: 'Weekly Schedule'!$L$13
Name LaborCost: 'Weekly Schedule'!$M$13
Name EmpName: 'Employees'!$B$5:$B$28
Name ForecastDay: 'Sales Forecast'!$B$5:$B$11
Name ForecastAmt: 'Sales Forecast'!$C$5:$C$11
Name ForecastSales: 'Sales Forecast'!$C$12
Name LaborTarget: 'Sales Forecast'!$D$12
Name OTHrs: 'Overtime'!$C$5:$C$7
Name OTHours: 'Overtime'!$C$8
Name FoodPct: 'Prime Cost'!$C$6
Name PrimeCost: 'Prime Cost'!$C$8
Name LaborDayAmt: 'Labor by Day'!$C$5:$C$11
Name HealthRange: 'Dashboard'!$C$13:$C$18

Sheet Start Here
A1: 🕐 RESTAURANT LABOR & SCHEDULING COMMAND CENTER™
A2: Schedule to your sales — and never over-spend on labor again.
B5: YOUR WHOLE LABOR PICTURE, IN ONE PLACE
B6: Labor is the cost you control every single week — and it's the second half of prime cost. This system makes it visible: build a weekly schedule and every employee's hours and cost calculate live, then the labor-cost engine divides labor by sales for a true labor %. Forecast sales to set a labor target, track sales per labor hour, watch overtime, and roll food cost + labor into a prime-cost number — all in ONE premium Google Sheets & Excel system built for restaurants.
B11: START HERE — 6 QUICK STEPS
B12: 1. Open Settings — set your target labor % & sales-per-hour goal.
B13: 2. Add your team in Employees; set roles & wages.
B14: 3. Build the Weekly Schedule — hours & cost calculate as you type.
B15: 4. Forecast sales; the labor target shows what you can spend.
B16: 5. Watch Sales-per-Labor-Hour, Overtime & Prime Cost.
B17: 6. Check the Dashboard: labor %, SPLH & a Labor Score.
B20: GOOD TO KNOW
B21: Sample data for a fictional restaurant (Maple & Ash) is included so you can see how it all connects — just type over it with your own team and hours. Labor % and prime cost are the two numbers that decide whether a shift makes money, and they roll into a live Labor Score. Twelve matching printable pages (blank weekly schedule, roster, time-off request, tip sheet & more) are included. This is a business tool, not financial, legal or HR advice — confirm wages, overtime rules and labor law with your own advisors.
B25: Every hour you schedule is a dollar you spend — schedule to the forecast.

Sheet Dashboard
A1: 🕐 LABOR & SCHEDULING COMMAND CENTER™
A2: Labor %, sales per labor hour, prime cost & a Score — your whole labor picture, at a glance.
B5: LABOR COST | D5: LABOR % | F5: WEEKLY SALES | H5: TOTAL HOURS | J5: SALES / LABOR HR | L5: EMPLOYEES
B6: =LaborCost | D6: =LaborPct | F6: =ForecastSales | H6: =TotalHours | J6: =SPLH | L6: =COUNTA(SchedName)
B8: LABOR TARGET | D8: VS TARGET | F8: AVG WAGE | H8: PRIME COST | J8: OT HOURS | L8: LABOR SCORE
B9: =LaborTarget | D9: =LaborTarget-LaborCost | F9: =AvgWage | H9: =PrimeCost | J9: =OTHours | L9: =IFERROR(AVERAGE(HealthRange),0)
B11: LABOR HEALTH | H11: LABOR BY DAY
B12: Check | C12: Score | D12: Status
B13: Labor on target | C13: =IFERROR(MIN(TargetLaborPct/LaborPct,1),0) | D13: =IF(C13>=0.85,"Strong",IF(C13>=0.6,"OK","Watch"))
B14: Sales per labor hr healthy | C14: =IFERROR(MIN(SPLH/SPLHGoal,1),0) | D14: =IF(C14>=0.85,"Strong",IF(C14>=0.6,"OK","Watch"))
B15: Overtime low | C15: =IFERROR(1-MIN(OTHours/OTLimit,1),0) | D15: =IF(C15>=0.85,"Strong",IF(C15>=0.6,"OK","Watch"))
B16: Prime cost in check | C16: =IFERROR(MIN(PrimeGoal/PrimeCost,1),0) | D16: =IF(C16>=0.85,"Strong",IF(C16>=0.6,"OK","Watch"))
B17: Schedule covered | C17: =IFERROR(COUNTIF(SchedHours,">0")/COUNTA(SchedName),0) | D17: =IF(C17>=0.85,"Strong",IF(C17>=0.6,"OK","Watch"))
B18: Wage in budget | C18: =IFERROR(MIN(WageGoal/AvgWage,1),0) | D18: =IF(C18>=0.85,"Strong",IF(C18>=0.6,"OK","Watch"))
B21: Labor & Scheduling Command Center™ — schedule to your sales, protect your prime cost.

Sheet Labor Cost Calc
A1: 🧮 LABOR COST CALC
A2: Scheduled labor ÷ sales = your true labor %. Sales ÷ hours = sales per labor hour.
B5: Line | C5: Amount
B6: Scheduled labor cost (from schedule) | C6: =LaborCost
B7: ÷ Weekly sales (from forecast) | C7: =ForecastSales
B8: =LABOR % | C8: =IFERROR(LaborCost/ForecastSales,0)
B9: Total scheduled hours | C9: =TotalHours
B10: Sales per labor hour | C10: =IFERROR(ForecastSales/TotalHours,0)
B11: Average wage | C11: =IFERROR(LaborCost/TotalHours,0)
B13: Change a single shift and your labor % updates instantly.

Sheet Weekly Schedule
A1: 🗓 WEEKLY SCHEDULE
A2: Type each shift's hours — weekly hours & labor cost calculate live for every employee.
B4: Employee | C4: Role | D4: Wage | E4: Mon | F4: Tue | G4: Wed | H4: Thu | I4: Fri | J4: Sat | K4: Sun | L4: Hours | M4: Cost
B5: Alex | C5: Line Cook | D5: 19 | E5: 8 | F5: 8 | G5: 8 | H5: 8 | I5: 8 | L5: =SUM(E5:K5) | M5: =D5*L5
B6: Bailey | C6: Line Cook | D6: 18 | F6: 8 | G6: 8 | H6: 8 | I6: 8 | J6: 8 | L6: =SUM(E6:K6) | M6: =D6*L6
B7: Casey | C7: Server | D7: 12 | E7: 6 | F7: 6 | H7: 6 | I7: 8 | J7: 8 | K7: 6 | L7: =SUM(E7:K7) | M7: =D7*L7
B8: Drew | C8: Server | D8: 12 | G8: 6 | H8: 6 | I8: 8 | J8: 8 | K8: 6 | L8: =SUM(E8:K8) | M8: =D8*L8
B9: Emerson | C9: Dishwasher | D9: 15 | E9: 6 | F9: 6 | G9: 6 | I9: 8 | J9: 8 | L9: =SUM(E9:K9) | M9: =D9*L9
B10: Finley | C10: Host | D10: 14 | E10: 5 | F10: 5 | G10: 5 | H10: 5 | I10: 6 | J10: 6 | L10: =SUM(E10:K10) | M10: =D10*L10
B11: Gray | C11: Bartender | D11: 13 | H11: 6 | I11: 8 | J11: 8 | K11: 6 | L11: =SUM(E11:K11) | M11: =D11*L11
B12: Harper | C12: Prep Cook | D12: 17 | E12: 8 | F12: 8 | G12: 8 | H12: 8 | L12: =SUM(E12:K12) | M12: =D12*L12
B13: WEEK TOTAL | L13: =SUM(SchedHours) | M13: =SUM(SchedCost)

Sheet Employees
A1: 👥 EMPLOYEES
A2: Your team — role, wage & status. Hours come from the Weekly Schedule.
B4: Name | C4: Role | D4: Wage | E4: Status
B5: Alex | C5: Line Cook | D5: 19 | E5: Full-time
B6: Bailey | C6: Line Cook | D6: 18 | E6: Full-time
B7: Casey | C7: Server | D7: 12 | E7: Full-time
B8: Drew | C8: Server | D8: 12 | E8: Part-time
B9: Emerson | C9: Dishwasher | D9: 15 | E9: Part-time
B10: Finley | C10: Host | D10: 14 | E10: Part-time
B11: Gray | C11: Bartender | D11: 13 | E11: Part-time
B12: Harper | C12: Prep Cook | D12: 17 | E12: Part-time

Sheet Sales Forecast
A1: 📈 SALES FORECAST
A2: Forecast sales by day → a labor target (at your target %) and the hours it buys.
B4: Day | C4: Forecast Sales | D4: Labor Target | E4: Target Hrs
B5: Mon | C5: 1500 | D5: =C5*TargetLaborPct | E5: =IFERROR(D5/WageGoal,0)
B6: Tue | C6: 1700 | D6: =C6*TargetLaborPct | E6: =IFERROR(D6/WageGoal,0)
B7: Wed | C7: 1800 | D7: =C7*TargetLaborPct | E7: =IFERROR(D7/WageGoal,0)
B8: Thu | C8: 2100 | D8: =C8*TargetLaborPct | E8: =IFERROR(D8/WageGoal,0)
B9: Fri | C9: 2900 | D9: =C9*TargetLaborPct | E9: =IFERROR(D9/WageGoal,0)
B10: Sat | C10: 3200 | D10: =C10*TargetLaborPct | E10: =IFERROR(D10/WageGoal,0)
B11: Sun | C11: 1800 | D11: =C11*TargetLaborPct | E11: =IFERROR(D11/WageGoal,0)
B12: WEEK TOTAL | C12: =SUM(C5:C11) | D12: =SUM(D5:D11)

Sheet Sales per Labor Hr
A1: ⚡ SALES PER LABOR HOUR
A2: The productivity number — each day's sales ÷ labor hours. Higher is a leaner shift.
B4: Day | C4: Sales | D4: Labor Hrs | E4: SPLH
B5: Mon | C5: 1500 | D5: =SUM('Weekly Schedule'!E5:E12) | E5: =IFERROR(C5/D5,0)
B6: Tue | C6: 1700 | D6: =SUM('Weekly Schedule'!F5:F12) | E6: =IFERROR(C6/D6,0)
B7: Wed | C7: 1800 | D7: =SUM('Weekly Schedule'!G5:G12) | E7: =IFERROR(C7/D7,0)
B8: Thu | C8: 2100 | D8: =SUM('Weekly Schedule'!H5:H12) | E8: =IFERROR(C8/D8,0)
B9: Fri | C9: 2900 | D9: =SUM('Weekly Schedule'!I5:I12) | E9: =IFERROR(C9/D9,0)
B10: Sat | C10: 3200 | D10: =SUM('Weekly Schedule'!J5:J12) | E10: =IFERROR(C10/D10,0)
B11: Sun | C11: 1800 | D11: =SUM('Weekly Schedule'!K5:K12) | E11: =IFERROR(C11/D11,0)

Sheet Overtime
A1: ⏰ OVERTIME
A2: Hours over 40 cost time-and-a-half — watch this before it eats your labor budget.
B4: Employee | C4: OT Hours | D4: Wage | E4: OT Cost (1.5×)
B5: Alex | C5: 3 | D5: 19 | E5: =C5*D5*1.5
B6: Casey | C6: 2 | D6: 12 | E6: =C6*D6*1.5
B7: Emerson | C7: 1 | D7: 15 | E7: =C7*D7*1.5
B8: OT TOTALS | C8: =SUM(OTHrs) | E8: =SUM(E5:E7)

Sheet Roles & Rates
A1: 💲 ROLES & RATES
A2: Your pay scale — one wage per role, so every new hire starts on the right number.
B4: Role | C4: Wage / hr | D4: Notes
B5: Manager | C5: 28 | D5: Salary equivalent
B6: Line Cook | C6: 19 | D6: Station lead
B7: Prep Cook | C7: 17 | D7: AM prep
B8: Server | C8: 12 | D8: + tips
B9: Bartender | C9: 13 | D9: + tips
B10: Host | C10: 14 | D10: Front door
B11: Dishwasher | C11: 15 | D11: Back of house

Sheet Availability
A1: 📅 AVAILABILITY & TIME-OFF
A2: Who can't work when — check it before you publish the schedule.
B4: Employee | C4: Days Off | D4: Notes
B5: Alex | C5: Sat, Sun | D5: Weekends off
B6: Bailey | C6: Mon, Sun | D6: School Mon AM
B7: Casey | C7: Wed | D7: Class
B8: Drew | C8: Mon, Tue | D8: Second job
B9: Emerson | C9: Thu, Sun | D9: —
B10: Finley | C10: Sun | D10: —
B11: Gray | C11: Mon, Tue, Wed | D11: Part-time
B12: Harper | C12: Fri, Sat, Sun | D12: AM only

Sheet Prime Cost
A1: 🎯 PRIME COST
A2: Food cost % + labor % = prime cost — the single number that decides if a restaurant profits.
B5: Line | C5: Amount
B6: Food cost % (enter yours) | C6: 0.3
B7: + Labor % (from Labor Cost Calc) | C7: =LaborPct
B8: =PRIME COST | C8: =FoodPct+LaborPct
B10: Target prime cost | C10: =PrimeGoal
B12: Keep prime cost under 60-65% and there's room for rent, utilities & profit.

Sheet Tips
A1: 💵 TIPS & TIP-OUT
A2: Daily tips and the back-of-house tip-out — so the pool splits fair, every night.
B4: Day | C4: Tips | D4: Tip-out % | E4: Net Tips
B5: Mon | C5: 320 | D5: 0.15 | E5: =C5*(1-D5)
B6: Tue | C6: 360 | D6: 0.15 | E6: =C6*(1-D6)
B7: Wed | C7: 380 | D7: 0.15 | E7: =C7*(1-D7)
B8: Thu | C8: 520 | D8: 0.15 | E8: =C8*(1-D8)
B9: Fri | C9: 780 | D9: 0.15 | E9: =C9*(1-D9)
B10: Sat | C10: 860 | D10: 0.15 | E10: =C10*(1-D10)
B11: Sun | C11: 440 | D11: 0.15 | E11: =C11*(1-D11)
B12: WEEK TOTAL | C12: =SUM(C5:C11) | E12: =SUM(E5:E11)

Sheet Labor by Day
A1: 📊 LABOR BY DAY
A2: Each day's labor dollars & labor % against the forecast — spot the heavy days.
B4: Day | C4: Labor $ | D4: Labor %
B5: Mon | C5: =SUMPRODUCT('Weekly Schedule'!$D$5:$D$12,'Weekly Schedule'!E5:E12) | D5: =IFERROR(C5/INDEX(ForecastAmt,1),0)
B6: Tue | C6: =SUMPRODUCT('Weekly Schedule'!$D$5:$D$12,'Weekly Schedule'!F5:F12) | D6: =IFERROR(C6/INDEX(ForecastAmt,2),0)
B7: Wed | C7: =SUMPRODUCT('Weekly Schedule'!$D$5:$D$12,'Weekly Schedule'!G5:G12) | D7: =IFERROR(C7/INDEX(ForecastAmt,3),0)
B8: Thu | C8: =SUMPRODUCT('Weekly Schedule'!$D$5:$D$12,'Weekly Schedule'!H5:H12) | D8: =IFERROR(C8/INDEX(ForecastAmt,4),0)
B9: Fri | C9: =SUMPRODUCT('Weekly Schedule'!$D$5:$D$12,'Weekly Schedule'!I5:I12) | D9: =IFERROR(C9/INDEX(ForecastAmt,5),0)
B10: Sat | C10: =SUMPRODUCT('Weekly Schedule'!$D$5:$D$12,'Weekly Schedule'!J5:J12) | D10: =IFERROR(C10/INDEX(ForecastAmt,6),0)
B11: Sun | C11: =SUMPRODUCT('Weekly Schedule'!$D$5:$D$12,'Weekly Schedule'!K5:K12) | D11: =IFERROR(C11/INDEX(ForecastAmt,7),0)

Sheet Settings
A1: ⚙ SETTINGS
A2: Set your targets & lists once — every tab follows.
B5: YOUR TARGETS | E5: DROPDOWN LISTS
B6: Restaurant name | C6: Maple & Ash | E6: Role | F6: Status | G6: Yes / No
B7: Manager | C7: Jordan | E7: Manager | F7: Full-time | G7: Yes
B8: Target labor % | C8: 0.3 | E8: Line Cook | F8: Part-time | G8: No
B9: Sales-per-labor-hr goal | C9: 50 | E9: Prep Cook | F9: On-call
B10: Overtime limit (hrs) | C10: 10 | E10: Server | F10: New
B11: Prime-cost goal % | C11: 0.6 | E11: Bartender
B12: Avg-wage budget | C12: 16 | E12: Host
B13: Currency | C13: USD ($) | E13: Dishwasher
